datapipe/__init__.py
datapipe/cli.py
datapipe/compute.py
datapipe/datatable.py
datapipe/event_logger.py
datapipe/lints.py
datapipe/py.typed
datapipe/run_config.py
datapipe/sql_util.py
datapipe/types.py
datapipe/executor/__init__.py
datapipe/executor/ray.py
datapipe/meta/__init__.py
datapipe/meta/sql_meta.py
datapipe/migrations/__init__.py
datapipe/migrations/v013.py
datapipe/step/__init__.py
datapipe/step/batch_generate.py
datapipe/step/batch_transform.py
datapipe/step/datatable_transform.py
datapipe/step/update_external_table.py
datapipe/store/__init__.py
datapipe/store/database.py
datapipe/store/elastic.py
datapipe/store/filedir.py
datapipe/store/milvus.py
datapipe/store/neo4j.py
datapipe/store/pandas.py
datapipe/store/qdrant.py
datapipe/store/redis.py
datapipe/store/table_store.py
datapipe/store/tests/__init__.py
datapipe/store/tests/abstract.py
datapipe/store/tests/stubs.py
datapipe/tests/__init__.py
datapipe/tests/util.py
datapipe_core-0.14.6.dist-info/METADATA
datapipe_core-0.14.6.dist-info/WHEEL
datapipe_core-0.14.6.dist-info/entry_points.txt
datapipe_core-0.14.6.dist-info/licenses/LICENSE
datapipe_core-0.14.6.dist-info/RECORD
