Metadata-Version: 2.4
Name: datapipe-core
Version: 0.14.6
Summary: `datapipe` is a realtime incremental ETL library for Python application
Project-URL: Repository, https://github.com/epoch8/datapipe
Author-email: Andrey Tatarinov <a@tatarinov.co>
License-File: LICENSE
Requires-Python: <3.15,>=3.9
Requires-Dist: cityhash<0.5,>=0.4.2
Requires-Dist: click>=7.1.2
Requires-Dist: cloudpickle>=1.6.0
Requires-Dist: fsspec>=2021.11.1
Requires-Dist: numpy<3.0,>=1.21.0
Requires-Dist: opentelemetry-api<2,>=1.8.0
Requires-Dist: opentelemetry-instrumentation-sqlalchemy
Requires-Dist: opentelemetry-sdk<2,>=1.8.0
Requires-Dist: pandas>=1.2.0
Requires-Dist: pillow<11,>=10.0.0
Requires-Dist: psycopg2-binary>=2.8.4
Requires-Dist: pyyaml>=5.3.1
Requires-Dist: rich<14,>=13.3.2
Requires-Dist: sqlalchemy<3.0.0,>=1.4.0
Requires-Dist: tqdm-loggable<0.3,>=0.2
Requires-Dist: traceback-with-variables<3,>=2.0.4
Provides-Extra: elastic
Requires-Dist: elasticsearch>=8.17.1; extra == 'elastic'
Provides-Extra: excel
Requires-Dist: openpyxl>=3.0.7; extra == 'excel'
Requires-Dist: xlrd>=2.0.1; extra == 'excel'
Provides-Extra: gcp
Requires-Dist: opentelemetry-exporter-gcp-trace; extra == 'gcp'
Provides-Extra: gcsfs
Requires-Dist: gcsfs>=2021.11.1; extra == 'gcsfs'
Provides-Extra: milvus
Requires-Dist: pymilvus<3,>=2.0.2; extra == 'milvus'
Provides-Extra: neo4j
Requires-Dist: neo4j; extra == 'neo4j'
Provides-Extra: pyarrow
Requires-Dist: pyarrow[pyarrow]>=21.0.0; extra == 'pyarrow'
Provides-Extra: qdrant
Requires-Dist: qdrant-client<2,>=1.1.7; extra == 'qdrant'
Provides-Extra: ray
Requires-Dist: ray[default]<3,>=2.5.0; extra == 'ray'
Provides-Extra: redis
Requires-Dist: redis<5,>=4.3.4; extra == 'redis'
Provides-Extra: s3fs
Requires-Dist: s3fs>=2021.11.1; extra == 's3fs'
Provides-Extra: sqlite
Requires-Dist: pysqlite3-binary<0.6,>=0.5.0; (sys_platform != 'darwin') and extra == 'sqlite'
Requires-Dist: sqlalchemy-pysqlite3-binary<0.0.5,>=0.0.4; (sys_platform != 'darwin') and extra == 'sqlite'
